meep/__init__.py
meep/filelist.txt
meep/meep.py
meep-1.0.6.dist-info/DESCRIPTION.rst
meep-1.0.6.dist-info/METADATA
meep-1.0.6.dist-info/RECORD
meep-1.0.6.dist-info/WHEEL
meep-1.0.6.dist-info/entry_points.txt
meep-1.0.6.dist-info/metadata.json
meep-1.0.6.dist-info/top_level.txt
